README.md
setup.py
rahulnikamalpha/__init__.py
rahulnikamalpha/operation.py
rahulnikamalpha.egg-info/PKG-INFO
rahulnikamalpha.egg-info/SOURCES.txt
rahulnikamalpha.egg-info/dependency_links.txt
rahulnikamalpha.egg-info/not-zip-safe
rahulnikamalpha.egg-info/top_level.txt