Metadata-Version: 2.1
Name: rahulnikamalpha
Version: 0.11
Summary: operation & greeting library
Author-email: codewithrahulnikam@gmail.com
